first.py
nightchanges-0.1.dist-info/METADATA
nightchanges-0.1.dist-info/WHEEL
nightchanges-0.1.dist-info/top_level.txt
nightchanges-0.1.dist-info/RECORD
