Metadata-Version: 2.1
Name: nightchanges
Version: 0.1
Summary: Come on Zayn Malik
Home-page: UNKNOWN
Author: Amir Kidwai
Author-email: findamirkidwai@gmail.com
License: UNKNOWN
Platform: UNKNOWN
Classifier: Programming Language :: Python :: 3
Classifier: License :: OSI Approved :: MIT License
Classifier: Operating System :: OS Independent
Requires-Python: >=3.6
